tgmm/__init__.py
tgmm/gmm.py
tgmm/gmm_init.py
tgmm/metrics.py
tgmm/plotting.py
tgmm-0.1.7.dist-info/METADATA
tgmm-0.1.7.dist-info/WHEEL
tgmm-0.1.7.dist-info/top_level.txt
tgmm-0.1.7.dist-info/RECORD
