Metadata-Version: 2.4
Name: tgmm
Version: 0.1.7
Summary: A Gaussian Mixture Model (GMM) based on Expectation-Maximisation (EM) implemented in PyTorch
Home-page: https://github.com/adriansousapoza/TorchGMM
Author: Your Name
Author-email: adrian.sousapoza@gmail.com
Classifier: Programming Language :: Python :: 3
Classifier: License :: OSI Approved :: MIT License
Classifier: Operating System :: OS Independent
Requires-Python: >=3.6
Requires-Dist: torch>=2.5.1
Requires-Dist: numpy>=1.23.0
Requires-Dist: matplotlib>=3.10.1
Provides-Extra: docs
Requires-Dist: Sphinx>=8.2.3; extra == "docs"
Requires-Dist: Pygments>=2.19.1; extra == "docs"
Dynamic: author
Dynamic: author-email
Dynamic: classifier
Dynamic: description
Dynamic: description-content-type
Dynamic: home-page
Dynamic: provides-extra
Dynamic: requires-dist
Dynamic: requires-python
Dynamic: summary
